<?xml version="1.0" encoding="UTF-8"?>
<teamworks>
    <managedAsset id="61.690faa8b-6303-4b32-b941-3689a14361ec" name="8817f8fc-dd21-4286-8ff6-7e14081aae0c.zip">
        <lastModified>1488694860803</lastModified>
        <lastModifiedBy>Deepak</lastModifiedBy>
        <managedAssetId>61.690faa8b-6303-4b32-b941-3689a14361ec</managedAssetId>
        <assetUuid>c5ad107d-577b-40cc-99bd-26c8c4c49094</assetUuid>
        <mimeType>application/zip</mimeType>
        <charEncoding isNull="true" />
        <assetTypeCode>T</assetTypeCode>
        <length>28673</length>
        <localLastModification>0</localLastModification>
        <description isNull="true" />
        <isDocumentationFile>false</isDocumentationFile>
        <guid>ebcb99ff-a31b-4e45-9e19-9e4572c66242</guid>
        <versionId>d3c7974e-de72-4c8f-8a80-6ad4e467ff37</versionId>
    </managedAsset>
</teamworks>

